simplcal/__init__.py
simplcal/gui.py
simplcal-0.0.1.dist-info/METADATA
simplcal-0.0.1.dist-info/WHEEL
simplcal-0.0.1.dist-info/top_level.txt
simplcal-0.0.1.dist-info/RECORD
