Metadata-Version: 2.4
Name: simplcal
Version: 0.0.1
Summary: A simple calculator package with GUI
Author: Tanvir
Dynamic: author
Dynamic: summary
